testdrkv6/__init__.py
testdrkv6/hello.py
testdrkv6-1.0.0.dist-info/METADATA
testdrkv6-1.0.0.dist-info/WHEEL
testdrkv6-1.0.0.dist-info/top_level.txt
testdrkv6-1.0.0.dist-info/RECORD
